MANIFEST.in
README.rst
TODO.rst
setup.py
django_dynamicforms.egg-info/PKG-INFO
django_dynamicforms.egg-info/SOURCES.txt
django_dynamicforms.egg-info/dependency_links.txt
django_dynamicforms.egg-info/requires.txt
django_dynamicforms.egg-info/top_level.txt
dynamicforms/__init__.py
dynamicforms/admin.py
dynamicforms/forms.py
dynamicforms/models.py
dynamicforms/tests.py
dynamicforms/urls.py
dynamicforms/views.py
dynamicforms/templates/dynamicforms/_form.html
dynamicforms/templates/dynamicforms/form.html
dynamicforms/templates/dynamicforms/notification.eml
dynamicforms/templatetags/__init__.py
dynamicforms/templatetags/dynamicforms_tags.py