Metadata-Version: 1.0
Name: django-dynamicforms
Version: 0.1.2
Summary: Dynamically add forms to your site through the admin interface.
Home-page: https://github.com/roalddevries/django-dynamicforms/
Author: Roald de Vries
Author-email: roald@go2people.nl
License: LICENSE.txt
Platform: UNKNOWN
